{"extVersion":"1.28.27","name":"Instagram Username Scraper","icon":"riGlobalLine","table":[],"version":"1.28.27","drawflow":{"edges":[{"data":{},"events":{},"id":"vueflow__edge-z6z7h4yz6z7h4y-output-1-4sb18x24sb18x2-input-1","markerEnd":"arrowclosed","selectable":true,"source":"z6z7h4y","sourceHandle":"z6z7h4y-output-1","sourceX":327.1946557892236,"sourceY":397.6333029085643,"target":"4sb18x2","targetHandle":"4sb18x2-input-1","targetX":637.2137588565965,"targetY":385.317698820452,"type":"custom","updatable":true},{"data":{},"events":{},"id":"vueflow__edge-4sb18x24sb18x2-output-1-1qqqj381qqqj38-input-1","markerEnd":"arrowclosed","selectable":true,"source":"4sb18x2","sourceHandle":"4sb18x2-output-1","sourceX":869.2137588565965,"sourceY":385.317698820452,"target":"1qqqj38","targetHandle":"1qqqj38-input-1","targetX":897.2653627230648,"targetY":377.9902339556743,"type":"custom","updatable":true},{"data":{},"events":{},"id":"vueflow__edge-1qqqj381qqqj38-output-1-lzxztyklzxztyk-input-1","markerEnd":"arrowclosed","selectable":true,"source":"1qqqj38","sourceHandle":"1qqqj38-output-1","sourceX":1129.2653627230648,"sourceY":377.9902339556743,"target":"lzxztyk","targetHandle":"lzxztyk-input-1","targetX":1171.357441833695,"targetY":376.72713681691556,"type":"custom","updatable":true},{"data":{},"events":{},"id":"vueflow__edge-lzxztyklzxztyk-output-1-0n3r2jw0n3r2jw-input-1","markerEnd":"arrowclosed","selectable":true,"source":"lzxztyk","sourceHandle":"lzxztyk-output-1","sourceX":1403.357441833695,"sourceY":376.72713681691556,"target":"0n3r2jw","targetHandle":"0n3r2jw-input-1","targetX":1474.5007551357744,"targetY":353.16602987898244,"type":"custom","updatable":true}],"nodes":[{"data":{"activeInInput":false,"contextMenuName":"","contextTypes":[],"date":"","days":[],"delay":5,"description":"","disableBlock":false,"interval":60,"isUrlRegex":false,"observeElement":{"baseElOptions":{"attributeFilter":[],"attributes":false,"characterData":false,"childList":true,"subtree":false},"baseSelector":"","matchPattern":"","selector":"","targetOptions":{"attributeFilter":[],"attributes":false,"characterData":false,"childList":true,"subtree":false}},"parameters":[],"preferParamsInTab":false,"shortcut":"","time":"00:00","type":"manual","url":""},"events":{},"id":"z6z7h4y","label":"trigger","position":{"x":115.19465578922359,"y":361.6333029085643},"type":"BlockBasic"},{"data":{"disableBlock":false},"events":{},"id":"4sb18x2","label":"active-tab","position":{"x":657.2137588565965,"y":349.317698820452},"type":"BlockBasic"},{"data":{"actionElMaxWaitTime":5,"actionElSelector":"","actionPageMaxWaitTime":10,"description":"","disableBlock":false,"findBy":"cssSelector","loadMoreAction":"none","loopId":"WiELJW","maxLoop":"0","reverseLoop":false,"scrollToBottom":true,"selector":".xjp7ctv:nth-child(4) > .x9f619 > .x9f619 > div","waitForSelector":false,"waitSelectorTimeout":5000},"events":{},"id":"1qqqj38","label":"loop-elements","position":{"x":917.2653627230648,"y":341.9902339556743},"type":"BlockBasic"},{"data":{"addExtraRow":false,"assignVariable":false,"dataColumn":"ung3f","description":"","disableBlock":false,"extraRowDataColumn":"","extraRowValue":"","findBy":"cssSelector","includeTags":false,"markEl":false,"multiple":false,"prefixText":"","regex":"","regexExp":[],"saveData":true,"selector":"{{loopData@WiELJW}} > .x9f619 > .x9f619 > .x9f619 > .x9f619 > .x9f619 > .x9f619 > .x1lliihq > .x1lliihq","suffixText":"","useTextContent":false,"variableName":"","waitForSelector":false,"waitSelectorTimeout":5000},"events":{},"id":"lzxztyk","label":"get-text","position":{"x":1191.357441833695,"y":340.72713681691556},"type":"BlockBasic"},{"data":{"clearLoop":false,"disableBlock":false,"loopId":"WiELJW"},"events":{},"id":"0n3r2jw","label":"loop-breakpoint","position":{"x":1494.5007551357744,"y":277.57227987898244},"type":"BlockLoopBreakpoint"}],"position":[-521,74],"viewport":{"x":-521,"y":74,"zoom":1},"zoom":1},"settings":{"blockDelay":0,"debugMode":false,"defaultColumnName":"column","execContext":"popup","executedBlockOnWeb":false,"inputAutocomplete":true,"insertDefaultColumn":false,"notification":true,"onError":"stop-workflow","publicId":"","restartTimes":3,"reuseLastState":false,"saveLog":true},"globalData":"{\n\t\"key\": \"value\"\n}","description":"Scrape Instagram username","includedWorkflows":{}}